[{"update_date": "2015/01/12", "name": "\u4eba\u9ad4\u5668\u5b98\u4fdd\u5b58\u5eab\u8a31\u53ef\u8cc7\u6599\u96c6", "the_url": "http://data.fda.gov.tw/frontsite/data/DataAction.do?method=doDetail&infoId=67", "the_type": "\u98a8\u96aa\u7ba1\u7406", "provider": "\u98a8\u96aa\u7ba1\u7406\u7d44", "the_id": "67", "columns": ["\u6a5f\u69cb\u540d\u7a31", "\u4fdd\u5b58\u5eab\u985e\u5225", "\u4fdd\u5b58\u5eab\u8a2d\u7f6e\u5730\u9ede"], "desc": "\r\n            \u4ee5\u79fb\u690d\u70ba\u76ee\u7684\uff0c\u5f9e\u4e8b\u4eba\u9ad4\u5668\u5b98(\u542b\u4eba\u9ad4\u7d44\u7e54\u3001\u7d30\u80de)\u53ca\u5176\u884d\u751f\u7269\u4e4b\u8655\u7406\u6216\u4fdd\u5b58\uff0c\u61c9\u4f9d\u4eba\u9ad4\u5668\u5b98\u4fdd\u5b58\u5eab\u7ba1\u7406\u8fa6\u6cd5\u7533\u8acb\u8a2d\u7f6e\u4eba\u9ad4\u5668\u5b98\u4fdd\u5b58\u5eab(\u7c21\u7a31\u4fdd\u5b58\u5eab)\u3002\u6a5f\u69cb\u4f9d\u898f\u5b9a\u9032\u884c\u7533\u8acb\u5f8c\uff0c\u7d93\u672c\u7f72\u6587\u4ef6\u5be9\u67e5\u53ca\u5be6\u5730\u5c65\u52d8\u6838\u53ef\u8005\uff0c\u5f97\u4eba\u9ad4\u5668\u5b98\u4fdd\u5b58\u5eab\u8a2d\u7f6e\u8a31\u53ef\uff0c\u540d\u55ae\u5c07\u4f9d\u6d41\u7a0b\u516c\u544a\u65bc\u7db2\u8def\u3002\r\n        "}]